discordSuperUtils/Base.py
discordSuperUtils/Database.py
discordSuperUtils/Leveling.py
discordSuperUtils/Music.py
discordSuperUtils/Paginator.py
discordSuperUtils/ReactionRoles.py
discordSuperUtils/__init__.py
discordSuperUtils-0.0.8.dist-info/LICENSE
discordSuperUtils-0.0.8.dist-info/METADATA
discordSuperUtils-0.0.8.dist-info/WHEEL
discordSuperUtils-0.0.8.dist-info/top_level.txt
discordSuperUtils-0.0.8.dist-info/RECORD
